notify/__init__.py
notify/_notify.cp36-win32.pyd
winnotify-0.1.0.dist-info/METADATA
winnotify-0.1.0.dist-info/WHEEL
winnotify-0.1.0.dist-info/top_level.txt
winnotify-0.1.0.dist-info/RECORD
